sticker_tools/__init__.py
sticker_tools/cli_interface.py
sticker_tools/convert_optimize.py
sticker_tools/patch_duration.py
sticker_tools-1.1.6.dist-info/METADATA
sticker_tools-1.1.6.dist-info/WHEEL
sticker_tools-1.1.6.dist-info/entry_points.txt
sticker_tools-1.1.6.dist-info/RECORD
