Metadata-Version: 2.3
Name: sticker-tools
Version: 1.1.6
Summary: 
Author: vbidula
Author-email: vadym.bidula@gmail.com
Requires-Python: >=3.12
Classifier: Programming Language :: Python :: 3
Classifier: Programming Language :: Python :: 3.12
Classifier: Programming Language :: Python :: 3.13
Provides-Extra: gui
Requires-Dist: pyqt6 (>=6.9.1,<7.0.0) ; extra == "gui"
